Workbook

Sheet Vendor_Data
A1: Invoice_ID | B1: Invoice_Date | C1: Vendor_Name | D1: Department | E1: Category | F1: Amount | G1: Status | H1: Payment_Method | I1: Month | J1: Month_Num
A2: 1 | B2: 45296 | C2: Dell Technologies | D2: IT | E2: Hardware | F2: 12500 | G2: PAID | H2: ACH | I2: =TEXT(B2,"MMM-YYYY") -> Jan-2024 | J2: =MONTH(B2) -> 1
A3: 2 | B3: 45303 | C3: Staples Business | D3: Operations | E3: Office Supplies | F3: 3200 | G3: PAID | H3: Check | I3: =TEXT(B3,"MMM-YYYY") -> Jan-2024 | J3: =MONTH(B3) -> 1
A4: 3 | B4: 45309 | C4: Iron Mountain | D4: Compliance | E4: Storage | F4: 8750 | G4: PENDING | I4: =TEXT(B4,"MMM-YYYY") -> Jan-2024 | J4: =MONTH(B4) -> 1
A5: 4 | B5: 45324 | C5: Salesforce Inc | D5: Sales | E5: Software | F5: 15000 | G5: PAID | H5: ACH | I5: =TEXT(B5,"MMM-YYYY") -> Feb-2024 | J5: =MONTH(B5) -> 2
A6: 5 | B6: 45336 | C6: WeWork | D6: Facilities | E6: Real Estate | F6: 22000 | G6: DISPUTED | I6: =TEXT(B6,"MMM-YYYY") -> Feb-2024 | J6: =MONTH(B6) -> 2
A7: 6 | B7: 45342 | C7: Oracle Corp | D7: IT | E7: Software | F7: 18500 | G7: PAID | H7: Wire | I7: =TEXT(B7,"MMM-YYYY") -> Feb-2024 | J7: =MONTH(B7) -> 2
A8: 7 | B8: 45352 | C8: FedEx | D8: Operations | E8: Shipping | F8: 4100 | G8: PAID | H8: ACH | I8: =TEXT(B8,"MMM-YYYY") -> Mar-2024 | J8: =MONTH(B8) -> 3
A9: 8 | B9: 45366 | C9: Deloitte | D9: Finance | E9: Professional Services | F9: 45000 | G9: PENDING | I9: =TEXT(B9,"MMM-YYYY") -> Mar-2024 | J9: =MONTH(B9) -> 3
A10: 9 | B10: 45373 | C10: AT&T | D10: IT | E10: Telecom | F10: 6800 | G10: PAID | H10: Check | I10: =TEXT(B10,"MMM-YYYY") -> Mar-2024 | J10: =MONTH(B10) -> 3
A11: 10 | B11: 45383 | C11: WeWork | D11: Facilities | E11: Real Estate | F11: 22000 | G11: PAID | H11: ACH | I11: =TEXT(B11,"MMM-YYYY") -> Apr-2024 | J11: =MONTH(B11) -> 4
A12: 11 | B12: 45392 | C12: Merck KGaA | D12: Finance | E12: Consulting | F12: 11200 | G12: PAID | H12: Wire | I12: =TEXT(B12,"MMM-YYYY") -> Apr-2024 | J12: =MONTH(B12) -> 4
A13: 12 | B13: 45400 | C13: Grainger | D13: Operations | E13: Maintenance | F13: 5600 | G13: PAID | H13: ACH | I13: =TEXT(B13,"MMM-YYYY") -> Apr-2024 | J13: =MONTH(B13) -> 4
A14: 13 | B14: 45414 | C14: Microsoft | D14: IT | E14: Software | F14: 9800 | G14: PAID | H14: ACH | I14: =TEXT(B14,"MMM-YYYY") -> May-2024 | J14: =MONTH(B14) -> 5
A15: 14 | B15: 45427 | C15: Cintas | D15: Facilities | E15: Uniforms | F15: 3400 | G15: PAID | H15: Check | I15: =TEXT(B15,"MMM-YYYY") -> May-2024 | J15: =MONTH(B15) -> 5
A16: 15 | B16: 45434 | C16: PwC | D16: Finance | E16: Professional Services | F16: 38000 | G16: PENDING | I16: =TEXT(B16,"MMM-YYYY") -> May-2024 | J16: =MONTH(B16) -> 5

Sheet Pivot Tables
A1: Status | B1: PENDING
A3: Department | B3: Sum of Amount | F3: Month_Num | G3: Month | H3: Sum of Amount
A4: Compliance | B4: 8750 | F4: 1 | G4: Jan-2024 | H4: 24450
A5: Finance | B5: 83000 | F5: 2 | G5: Feb-2024 | H5: 55500
A6: Grand Total | B6: 91750 | F6: 3 | G6: Mar-2024 | H6: 55900
F7: 4 | G7: Apr-2024 | H7: 38800
F8: 5 | G8: May-2024 | H8: 51200
F9: Grand Total | H9: 225850
A16: Category | B16: Sum of Amount
A17: Consulting | B17: 11200
A18: Hardware | B18: 12500
A19: Maintenance | B19: 5600
A20: Office Supplies | B20: 3200
A21: Professional Services | B21: 83000
A22: Real Estate | B22: 44000
A23: Shipping | B23: 4100
A24: Software | B24: 43300
A25: Storage | B25: 8750
A26: Telecom | B26: 6800
A27: Uniforms | B27: 3400
A28: Grand Total | B28: 225850

Sheet Dashboard
A1: Total Invoices | B1: =COUNTA(Vendor_Data!A:A)-1 -> 15
A2: Total Spend | B2: =SUM(Vendor_Data!F:F) -> 225850
A3: Total Paid | B3: =SUMIF(Vendor_Data!G:G,"PAID",Vendor_Data!F:F) -> 112100
A4: Total Pending | B4: =SUMIF(Vendor_Data!G:G,"PENDING",Vendor_Data!F:F) -> 91750
A5: Total Disputed | B5: =SUMIF(Vendor_Data!G:G,"DISPUTED",Vendor_Data!F:F) -> 22000
A6: Outstanding Balance | B6: =B4+B5 -> 113750
